README.md
setup.cfg
setup.py
distrianalysis/Binomialdistribution.py
distrianalysis/Gaussiandistribution.py
distrianalysis/Generaldistribution.py
distrianalysis/__init__.py
distrianalysis.egg-info/PKG-INFO
distrianalysis.egg-info/SOURCES.txt
distrianalysis.egg-info/dependency_links.txt
distrianalysis.egg-info/not-zip-safe
distrianalysis.egg-info/top_level.txt