Metadata-Version: 1.0
Name: distrianalysis
Version: 0.2
Summary: Gaussian and Binomial Distribution analysis tools
Home-page: UNKNOWN
Author: Prateek Gupta
Author-email: dpsrateek@gmail.com
License: UNKNOWN
Platform: UNKNOWN
